grunt4django/__init__.py
grunt4django/middleware.py
grunt4django/management/__init__.py
grunt4django/management/commands/__init__.py
grunt4django/management/commands/gruntserver.py
grunt4django-1.0.4.dist-info/DESCRIPTION.rst
grunt4django-1.0.4.dist-info/METADATA
grunt4django-1.0.4.dist-info/RECORD
grunt4django-1.0.4.dist-info/WHEEL
grunt4django-1.0.4.dist-info/metadata.json
grunt4django-1.0.4.dist-info/top_level.txt
