Metadata-Version: 2.0
Name: grunt4django
Version: 1.0.4
Summary: 包含django的runserver命令，还有针对html的中间件(添加livereload)
Home-page: https://github.com/lh2907883/grunt4django
Author: lihao
Author-email: lihao12518@163.com
License: UNKNOWN
Platform: UNKNOWN
